bilibiliupload/__init__.py
bilibiliupload/bilibili.py
bilibiliupload-0.2.4.dist-info/LICENSE.md
bilibiliupload-0.2.4.dist-info/METADATA
bilibiliupload-0.2.4.dist-info/WHEEL
bilibiliupload-0.2.4.dist-info/top_level.txt
bilibiliupload-0.2.4.dist-info/RECORD
