Metadata-Version: 2.1
Name: bilibiliupload
Version: 0.2.4
Summary: Upload video to bilibili under command-line interface
Home-page: https://github.com/comwrg/bilibiliupload
Author: comwrg
Author-email: xcomwrg@gmail.com
License: MIT
Keywords: bilibili,upload
Platform: UNKNOWN
Classifier: License :: OSI Approved :: MIT License
Classifier: Programming Language :: Python
Classifier: Topic :: Internet :: WWW/HTTP
Requires-Dist: rsa
Requires-Dist: requests
